simplewsgi/__init__.py
simplewsgi/router.py
simplewsgi/simplewsgi.py
simplewsgi-0.0.4.dist-info/METADATA
simplewsgi-0.0.4.dist-info/WHEEL
simplewsgi-0.0.4.dist-info/top_level.txt
simplewsgi-0.0.4.dist-info/RECORD
